{
  "display": {
    "icon": {
      "item": "dimensional_expansion:emertyst_helmet"
    },
    "title": {
		"translate": "advancements.dimensional_expansion.cover_me_with_emertyst.title"
	},
    "description": {
		"translate": "advancements.dimensional_expansion.cover_me_with_emertyst.desc"
	}
  },
  "criteria": {
    "requirement": {
      "trigger": "minecraft:inventory_changed",
      "conditions": {
        "items": [
        	{
	            "items": [
	              "dimensional_expansion:emertyst_helmet"
	            ],
	            "count": {
	              "min": 1,
	              "max": 64
	            }
            },
            {
	            "items": [
	              "dimensional_expansion:emertyst_chestplate"
	            ],
	            "count": {
	              "min": 1,
	              "max": 64
	            }
            },
            {
	            "items": [
	              "dimensional_expansion:emertyst_leggings"
	            ],
	            "count": {
	              "min": 1,
	              "max": 64
	            }
	        },
	        {
	            "items": [
	              "dimensional_expansion:emertyst_boots"
	            ],
	            "count": {
	              "min": 1,
	              "max": 64
	            }
	        }
        ]
      }
    }
  },
  "rewards": {
    "experience": 50,
    "recipes": [
    ]
  },
  "parent": "dimensional_expansion:emertyst"
}